turbopuffer/__init__.py
turbopuffer/_base_client.py
turbopuffer/_client.py
turbopuffer/_compat.py
turbopuffer/_constants.py
turbopuffer/_exceptions.py
turbopuffer/_files.py
turbopuffer/_models.py
turbopuffer/_qs.py
turbopuffer/_resource.py
turbopuffer/_response.py
turbopuffer/_streaming.py
turbopuffer/_types.py
turbopuffer/_version.py
turbopuffer/pagination.py
turbopuffer/py.typed
turbopuffer/_utils/__init__.py
turbopuffer/_utils/_compat.py
turbopuffer/_utils/_datetime_parse.py
turbopuffer/_utils/_logs.py
turbopuffer/_utils/_proxy.py
turbopuffer/_utils/_reflection.py
turbopuffer/_utils/_resources_proxy.py
turbopuffer/_utils/_streams.py
turbopuffer/_utils/_sync.py
turbopuffer/_utils/_transform.py
turbopuffer/_utils/_typing.py
turbopuffer/_utils/_utils.py
turbopuffer/lib/.keep
turbopuffer/lib/json.py
turbopuffer/lib/namespace.py
turbopuffer/lib/performance.py
turbopuffer/lib/transport.py
turbopuffer/lib/transport_aiohttp.py
turbopuffer/lib/transport_httpx.py
turbopuffer/lib/transport_urllib3.py
turbopuffer/lib/vector.py
turbopuffer/resources/__init__.py
turbopuffer/resources/namespaces.py
turbopuffer/types/__init__.py
turbopuffer/types/aggregation_group.py
turbopuffer/types/attribute_schema_config.py
turbopuffer/types/attribute_schema_config_param.py
turbopuffer/types/attribute_schema_param.py
turbopuffer/types/attribute_type.py
turbopuffer/types/bm25_clause_params.py
turbopuffer/types/client_namespaces_params.py
turbopuffer/types/columns_param.py
turbopuffer/types/contains_all_tokens_filter_params.py
turbopuffer/types/custom.py
turbopuffer/types/distance_metric.py
turbopuffer/types/full_text_search.py
turbopuffer/types/full_text_search_config.py
turbopuffer/types/full_text_search_config_param.py
turbopuffer/types/full_text_search_param.py
turbopuffer/types/id.py
turbopuffer/types/id_param.py
turbopuffer/types/include_attributes_param.py
turbopuffer/types/language.py
turbopuffer/types/namespace_delete_all_response.py
turbopuffer-1.12.0.dist-info/METADATA
turbopuffer-1.12.0.dist-info/WHEEL
turbopuffer-1.12.0.dist-info/licenses/LICENSE
turbopuffer-1.12.0.dist-info/RECORD
