Metadata-Version: 2.3
Name: turbopuffer
Version: 1.12.0
Summary: The official Python library for the turbopuffer API
Project-URL: Homepage, https://github.com/turbopuffer/turbopuffer-python
Project-URL: Repository, https://github.com/turbopuffer/turbopuffer-python
Author-email: Turbopuffer <info@turbopuffer.com>
License: MIT
Classifier: Intended Audience :: Developers
Classifier: License :: OSI Approved :: MIT License
Classifier: Operating System :: MacOS
Classifier: Operating System :: Microsoft :: Windows
Classifier: Operating System :: OS Independent
Classifier: Operating System :: POSIX
Classifier: Operating System :: POSIX :: Linux
Classifier: Programming Language :: Python :: 3.9
Classifier: Programming Language :: Python :: 3.10
Classifier: Programming Language :: Python :: 3.11
Classifier: Programming Language :: Python :: 3.12
Classifier: Programming Language :: Python :: 3.13
Classifier: Programming Language :: Python :: 3.14
Classifier: Topic :: Software Development :: Libraries :: Python Modules
Classifier: Typing :: Typed
Requires-Python: >=3.9
Requires-Dist: aiohttp<4,>=3.10.11
Requires-Dist: anyio<5,>=3.5.0
Requires-Dist: distro<2,>=1.7.0
Requires-Dist: httpx<1,>=0.23.0
Requires-Dist: orjson<4,>=3.10.15
Requires-Dist: pybase64<2,>=1.4.1
Requires-Dist: pydantic<3,>=1.9.0
Requires-Dist: sniffio
Requires-Dist: typing-extensions<5,>=4.13
Provides-Extra: aiohttp
Requires-Dist: aiohttp; extra == 'aiohttp'
Requires-Dist: httpx-aiohttp>=0.1.9; extra == 'aiohttp'
Provides-Extra: fast
Provides-Extra: urllib3
Requires-Dist: urllib3<3,>=2.2.3; extra == 'urllib3'
